{
  "id": "qr_00460",
  "title": "A Complicated Goodbye",
  "category": "Romance",
  "version": 1,
  "content": "When Hannah received an opportunity to study overseas for a year, she and Ryan knew they faced a difficult decision. Neither wanted the other to give up an important dream. On their final evening together, they walked through the city where they had shared countless memories. Instead of making impossible promises, they agreed to support each other honestly, whatever the future might bring. Their goodbye was filled with both tears and hope. They understood that real love is not measured by how tightly we hold on to someone, but by how sincerely we encourage them to grow."
}