{
  "id": "qr_00399",
  "title": "The Stranger Who Knew Everything",
  "category": "Mystery",
  "version": 1,
  "content": "A quiet stranger began appearing at community meetings, greeting residents by name and remembering details about local events stretching back decades.\n\nPeople wondered how someone apparently new to town possessed such remarkable knowledge.\n\nRumors spread quickly.\n\nSome imagined he had secretly lived there for years. Others believed he had extraordinary investigative skills.\n\nEventually, librarian Helen recognized him.\n\nThe stranger had spent nearly forty years working in the city's historical archives, preserving newspapers, photographs, council records, and personal letters. Although thousands of residents had unknowingly benefited from his work, few had ever met him.\n\nHis knowledge came not from hidden surveillance or impossible memory but from decades spent protecting the town's history.\n\nThe greatest surprise was not how much he knew.\n\nIt was how invisible such an important contribution had remained."
}