{
  "id": "qr_00180",
  "title": "A Small Town in Italy",
  "category": "Travel",
  "version": 1,
  "content": "Instead of visiting major cities, Emma chose to spend several days in a small Italian town surrounded by vineyards and rolling hills. The pace of life felt slower, and residents greeted one another by name. She spent mornings exploring narrow streets and afternoons enjoying local cafés and family-owned restaurants. Without large crowds or famous attractions, the town offered a more authentic glimpse into everyday life. Emma enjoyed the simplicity of her routine and appreciated the warm hospitality she encountered. The experience showed her that some of the best travel destinations were not always the most famous."
}