{
  "id": "qr_00206",
  "title": "My Favorite App",
  "category": "Technology",
  "version": 1,
  "content": "My favorite app helps me stay organized every day. I use it to create task lists, set reminders, and plan my schedule. Every morning, I check the app to see what I need to do. When I finish a task, I mark it as complete. This gives me a sense of achievement and helps me stay motivated. The app is simple to use and works on both my phone and tablet. Because of it, I rarely forget important appointments or deadlines. It has become an important part of my daily routine."
}