{
  "id": "qr_00287",
  "title": "Living in a Digital World",
  "category": "Technology",
  "version": 1,
  "content": "The first thing many people see each morning is not the sunrise but a screen. Notifications announce new messages, calendars display appointments, and news feeds summarize events from around the world before breakfast has even ended.\n\nLiving in a digital world offers remarkable convenience. Information that once required hours of research can now be accessed within seconds. Friends separated by continents can speak face-to-face through video calls. Businesses operate across time zones, and students learn from experts they may never meet in person.\n\nYet convenience comes with complexity. The same technologies that connect people can also compete for their attention. Endless streams of content encourage constant engagement, making silence increasingly rare. As devices become more integrated into everyday life, individuals face new questions about privacy, balance, and well-being.\n\nDespite these challenges, technology itself remains neutral. Its impact depends largely on how people choose to use it. A smartphone can distract someone for hours or help them learn a new language. Social networks can spread misinformation or strengthen communities.\n\nLiving in a digital world requires more than technical literacy. It requires thoughtful decisions about what deserves attention, what should remain private, and how technology can support rather than control everyday life."
}